LICENCE.txt
MANIFEST.in
README.txt
setup.py
string_to_tense/__init__.py
string_to_tense/is_future.py
string_to_tense.egg-info/PKG-INFO
string_to_tense.egg-info/SOURCES.txt
string_to_tense.egg-info/dependency_links.txt
string_to_tense.egg-info/requires.txt
string_to_tense.egg-info/top_level.txt
string_to_tense/model_checkpoint/__init__.py
string_to_tense/model_checkpoint/enc_input.pkl
string_to_tense/model_checkpoint/model.pkl
string_to_tense/pattern/__init__.py
string_to_tense/pattern/helpers.py
string_to_tense/pattern/metrics.py
string_to_tense/pattern/db/__init__.py
string_to_tense/pattern/graph/__init__.py
string_to_tense/pattern/graph/commonsense.py
string_to_tense/pattern/server/__init__.py
string_to_tense/pattern/text/__init__.py
string_to_tense/pattern/text/search.py
string_to_tense/pattern/text/tree.py
string_to_tense/pattern/text/en/__init__.py
string_to_tense/pattern/text/en/__main__.py
string_to_tense/pattern/text/en/en-context.txt
string_to_tense/pattern/text/en/en-entities.txt
string_to_tense/pattern/text/en/en-frequency.txt
string_to_tense/pattern/text/en/en-lexicon.txt
string_to_tense/pattern/text/en/en-model.slp
string_to_tense/pattern/text/en/en-morphology.txt
string_to_tense/pattern/text/en/en-sentiment.xml
string_to_tense/pattern/text/en/en-spelling.txt
string_to_tense/pattern/text/en/en-verbs.txt
string_to_tense/pattern/text/en/inflect.py
string_to_tense/pattern/text/en/inflect_quantify.py
string_to_tense/pattern/text/en/modality.py
string_to_tense/pattern/text/en/wordlist/__init__.py
string_to_tense/pattern/text/en/wordlist/academic.txt
string_to_tense/pattern/text/en/wordlist/basic.txt
string_to_tense/pattern/text/en/wordlist/profanity.txt
string_to_tense/pattern/text/en/wordlist/stopwords.txt
string_to_tense/pattern/text/en/wordlist/time.txt
string_to_tense/pattern/text/en/wordnet/__init__.py
string_to_tense/pattern/text/en/wordnet/resnik-ic2.txt
string_to_tense/pattern/text/en/wordnet/resnik-ic3.txt
string_to_tense/pattern/vector/__init__.py
string_to_tense/pattern/vector/stemmer.py
string_to_tense/pattern/vector/svm/__init__.py
string_to_tense/pattern/vector/svm/liblinear.py
string_to_tense/pattern/vector/svm/liblinearutil.py
